app/__init__.py
app/__main__.py
app/config.py
app/controllers/__init__.py
app/controllers/base_controller.py
app/controllers/list_controller.py
app/dados/star-wars-planets.dd
app/exceptions/__init__.py
app/exceptions/base_exceptions.py
app/services/__init__.py
app/services/dados_service.py
dados-0.1.4.dist-info/DESCRIPTION.rst
dados-0.1.4.dist-info/METADATA
dados-0.1.4.dist-info/RECORD
dados-0.1.4.dist-info/WHEEL
dados-0.1.4.dist-info/entry_points.txt
dados-0.1.4.dist-info/metadata.json
dados-0.1.4.dist-info/top_level.txt
