Metadata-Version: 1.1
Name: dados
Version: 0.1.4
Summary: Random word generator
Home-page: https://github.com/jamrizzi/foundation
Author: Jam Risser
Author-email: jam@jamrizzi.com
License: MIT
Keywords: random word dice generator name server generate
Platform: UNKNOWN
Classifier: Development Status :: 4 - Beta
Classifier: Intended Audience :: Developers
Classifier: Topic :: Utilities
Classifier: License :: OSI Approved :: MIT License
Classifier: Programming Language :: Python :: 2
Classifier: Programming Language :: Python :: 2.7
Classifier: Programming Language :: Python :: 3
Classifier: Programming Language :: Python :: 3.3
Classifier: Programming Language :: Python :: 3.4
Classifier: Programming Language :: Python :: 3.5
